ytq/__init__.py
ytq/__main__.py
ytq/cli.py
ytq/core.py
ytq/db.py
ytq/embeddings.py
ytq/llm.py
ytq-0.1.dist-info/LICENSE
ytq-0.1.dist-info/METADATA
ytq-0.1.dist-info/WHEEL
ytq-0.1.dist-info/entry_points.txt
ytq-0.1.dist-info/top_level.txt
ytq-0.1.dist-info/RECORD
