Metadata-Version: 2.2
Name: ytq
Version: 0.1
Summary: Build knowledge base from YouTube video transcripts
Author: Lyubomir Georgiev
License: Apache-2.0
Project-URL: Homepage, https://github.com/lvg77/ytq
Project-URL: Changelog, https://github.com/lvg77/ytq/releases
Project-URL: Issues, https://github.com/lvg77/ytq/issues
Project-URL: CI, https://github.com/lvg77/ytq/actions
Classifier: License :: OSI Approved :: Apache Software License
Requires-Python: >=3.8
License-File: LICENSE
Requires-Dist: typer
Requires-Dist: yt-dlp
Requires-Dist: numpy
Requires-Dist: anthropic>=0.49.0
Requires-Dist: openai>=1.65.1
Requires-Dist: pydantic>=2.10.6
Requires-Dist: requests>=2.32.3
Provides-Extra: test
Requires-Dist: pytest; extra == "test"
